{"trump": 1908.0, "amp": 1372.0, "person": 1195.0, "new": 1124.0, "president": 988.0, "what": 966.0, "today": 931.0, "day": 913.0, "vote": 855.0, "year": 825.0, "covid": 753.0, "how": 749.0, "state": 717.0, "time": 670.0, "m": 648.0, "work": 623.0, "know": 612.0, "me": 580.0, "here": 569.0, "need": 563.0, "don": 543.0, "right": 540.0, "school": 538.0, "biden": 534.0, "life": 514.0, "worker": 502.0, "election": 495.0, "tell": 481.0, "join": 477.0, "week": 440.0, "black": 439.0, "call": 438.0, "break": 432.0, "ve": 431.0, "think": 424.0, "family": 417.0, "american": 402.0, "white": 398.0, "pandemic": 397.0, "woman": 394.0, "back": 377.0, "student": 375.0, "mask": 369.0, "support": 363.0, "win": 362.0, "report": 353.0, "history": 338.0, "watch": 337.0, "house": 335.0, "million": 331.0, "fire": 328.0, "even": 323.0, "start": 322.0, "health": 320.0, "being": 319.0, "live": 318.0, "community": 314.0, "let": 311.0, "force": 310.0, "thing": 309.0, "plan": 308.0, "show": 306.0, "talk": 299.0, "great": 298.0, "americans": 294.0, "america": 293.0, "learn": 293.0, "coronavirus": 292.0, "month": 290.0, "news": 286.0, "lose": 285.0, "country": 282.0, "public": 279.0, "voter": 276.0, "fight": 274.0, "good": 273.0, "job": 266.0, "change": 265.0, "read": 262.0, "thank": 261.0, "care": 261.0, "national": 258.0, "covid19": 255.0, "federal": 253.0, "please": 252.0, "tonight": 248.0, "union": 248.0, "act": 248.0, "find": 247.0, "big": 246.0, "hear": 246.0, "world": 245.0, "justice": 245.0, "book": 242.0, "share": 241.0, "pay": 238.0, "police": 238.0, "come": 237.0, "donald": 237.0, "remember": 235.0, "stop": 235.0, "law": 234.0, "story": 234.0, "ll": 233.0, "city": 231.0, "write": 229.0, "man": 229.0, "vaccine": 226.0, "september": 224.0, "wear": 221.0, "long": 220.0, "death": 219.0, "face": 218.0, "bill": 217.0, "republican": 215.0, "love": 213.0, "test": 213.0, "sign": 212.0, "lead": 211.0, "lie": 211.0, "include": 210.0, "ago": 210.0, "keep": 210.0, "political": 210.0, "case": 208.0, "play": 207.0, "barr": 207.0, "feel": 206.0, "child": 206.0, "official": 206.0, "game": 206.0, "ballot": 205.0, "home": 204.0, "honor": 204.0, "wildfire": 204.0, "end": 203.0, "didn": 202.0, "member": 201.0, "power": 200.0, "team": 199.0, "put": 198.0, "high": 197.0, "die": 197.0, "look": 195.0, "night": 195.0, "safe": 193.0, "joe": 192.0, "service": 191.0, "give": 190.0, "stand": 190.0, "leave": 189.0, "bad": 188.0, "pass": 188.0, "check": 188.0, "order": 188.0, "continue": 187.0, "court": 185.0, "nation": 185.0, "issue": 182.0, "early": 181.0, "campaign": 181.0, "government": 181.0, "teacher": 180.0, "important": 180.0, "friend": 180.0, "clear": 180.0, "unite": 179.0, "has_been": 178.0, "ice": 176.0, "senate": 176.0, "question": 173.0, "morning": 173.0, "late": 172.0, "attack": 172.0, "open": 171.0, "fact": 171.0, "leader": 171.0, "kill": 170.0, "climate": 170.0, "labor": 169.0, "free": 169.0, "protect": 169.0, "bring": 169.0, "point": 169.0, "mean": 168.0, "run": 168.0, "sally": 168.0, "woodward": 167.0, "human": 167.0, "own": 166.0, "doesn": 163.0, "social": 162.0, "speak": 162.0, "season": 162.0, "believe": 161.0, "register": 159.0, "hour": 159.0, "tomorrow": 158.0, "video": 157.0, "mail": 156.0, "update": 154.0, "happen": 153.0, "meet": 153.0, "director": 153.0, "part": 151.0, "hold": 151.0, "nurse": 150.0, "event": 148.0, "fall": 148.0, "provide": 147.0, "interview": 146.0, "record": 146.0, "officer": 146.0, "staff": 145.0, "crisis": 145.0, "begin": 145.0, "proud": 144.0, "press": 144.0, "air": 143.0, "action": 142.0, "general": 142.0, "send": 142.0, "response": 141.0, "business": 140.0, "well": 139.0, "ready": 139.0, "administration": 139.0, "claim": 138.0, "spread": 137.0, "sept": 137.0, "policy": 137.0, "isn": 137.0, "group": 137.0, "matter": 136.0, "california": 136.0, "discuss": 136.0, "hard": 135.0, "close": 135.0, "judge": 135.0, "demand": 135.0, "save": 135.0, "democrat": 134.0, "cdc": 134.0, "announce": 134.0, "word": 134.0, "create": 133.0, "real": 133.0, "congress": 133.0, "old": 133.0, "program": 133.0, "center": 133.0, "county": 132.0, "kid": 132.0, "single": 132.0, "poll": 132.0, "fund": 131.0, "low": 131.0, "virus": 131.0, "happy": 129.0, "hope": 129.0, "listen": 129.0, "moment": 129.0, "effort": 128.0, "release": 128.0, "full": 128.0, "young": 127.0, "top": 127.0, "miss": 127.0, "florida": 126.0, "excite": 125.0, "cover": 122.0, "return": 122.0, "name": 122.0, "build": 122.0, "tweet": 121.0, "threat": 121.0, "mass": 121.0, "college": 120.0, "yesterday": 120.0, "past": 120.0, "protest": 120.0, "tax": 119.0, "trust": 119.0, "science": 119.0, "stay": 119.0, "turn": 118.0, "hurricane": 117.0, "spend": 117.0, "forget": 117.0, "medium": 117.0, "deal": 117.0, "guy": 116.0, "line": 116.0, "virtual": 116.0, "rule": 115.0, "strike": 115.0, "conference": 115.0, "party": 114.0, "receive": 114.0, "fbi": 114.0, "racism": 113.0, "safety": 113.0, "thousand": 113.0, "large": 113.0, "lot": 111.0, "town": 111.0, "few": 110.0, "race": 110.0, "fail": 109.0, "move": 109.0, "ad": 109.0, "shoot": 109.0, "parent": 109.0, "education": 108.0, "teach": 106.0, "burn": 106.0, "place": 106.0, "monday": 105.0, "hand": 105.0, "investigation": 105.0, "truth": 105.0, "class": 105.0, "far": 105.0, "oregon": 104.0, "conversation": 103.0, "block": 103.0, "flood": 103.0, "rate": 103.0, "understand": 103.0, "democracy": 102.0, "area": 102.0, "york": 102.0, "wait": 102.0, "problem": 101.0, "dr": 101.0, "hall": 101.0, "west": 100.0, "voice": 100.0, "hysterectomy": 100.0, "serve": 100.0, "special": 100.0, "system": 99.0, "god": 99.0, "visit": 99.0, "host": 99.0, "allow": 99.0, "post": 99.0, "attorney": 99.0, "billion": 98.0, "firefighter": 98.0, "wage": 98.0, "pm": 98.0, "count": 98.0, "relief": 98.0, "head": 97.0, "war": 97.0, "decision": 97.0, "reopen": 97.0, "south": 96.0, "challenge": 96.0, "statement": 96.0, "football": 96.0, "future": 96.0, "resource": 95.0, "project": 95.0, "experience": 95.0, "confirm": 95.0, "small": 94.0, "immigrant": 94.0, "company": 94.0, "peace": 94.0, "respond": 94.0, "tune": 93.0, "literally": 93.0, "university": 93.0, "risk": 93.0, "set": 92.0, "strong": 92.0, "hit": 92.0, "wow": 92.0, "november": 91.0, "pres": 91.0, "celebrate": 91.0, "impact": 91.0, "step": 91.0, "decade": 90.0, "cause": 90.0, "north": 90.0, "less": 90.0, "answer": 89.0, "positive": 89.0, "second": 89.0, "employee": 88.0, "office": 88.0, "online": 88.0, "datum": 88.0, "piece": 87.0, "protection": 87.0, "politics": 87.0, "true": 86.0, "hospital": 86.0, "penny": 86.0, "feature": 86.0, "expect": 86.0, "anti": 86.0, "reason": 86.0, "racial": 86.0, "rally": 85.0, "candidate": 85.0, "essential": 85.0, "blue": 85.0, "department": 85.0, "charge": 84.0, "key": 84.0, "result": 84.0, "local": 84.0, "level": 84.0, "middle": 84.0, "due": 84.0, "ten": 84.0, "raise": 83.0, "threaten": 83.0, "smoke": 83.0, "senator": 83.0, "presidential": 83.0, "veteran": 83.0, "message": 83.0, "prepare": 83.0, "slavery": 83.0, "base": 83.0, "numb": 82.0, "constitution": 82.0, "condition": 82.0, "cut": 82.0, "congratulation": 81.0, "forward": 81.0, "green": 81.0, "reminder": 81.0, "hero": 80.0, "reveal": 80.0, "economic": 80.0, "historic": 80.0, "economy": 80.0, "money": 80.0, "bob": 79.0, "jersey": 79.0, "facebook": 79.0, "access": 79.0, "career": 79.0, "georgia": 78.0, "concern": 78.0, "twitter": 78.0, "deserve": 78.0, "gt": 78.0, "welcome": 78.0, "scientist": 77.0, "income": 77.0, "player": 77.0, "district": 77.0, "nyc": 77.0, "drop": 77.0, "mark": 77.0, "critical": 77.0, "information": 76.0, "launch": 75.0, "sport": 75.0, "staffer": 75.0, "movement": 75.0, "ensure": 75.0, "military": 75.0, "carolina": 75.0, "educator": 75.0, "active": 75.0, "redfield": 75.0, "arrest": 75.0, "governor": 74.0, "agree": 74.0, "folk": 74.0, "minute": 74.0, "address": 74.0, "security": 74.0, "offer": 74.0, "detention": 73.0, "sit": 73.0, "friday": 73.0, "crime": 73.0, "coast": 73.0, "census": 73.0, "rise": 73.0, "deadly": 73.0, "dangerous": 73.0, "cnn": 72.0, "hundred": 72.0, "task": 72.0, "remain": 72.0, "study": 72.0, "murder": 71.0, "involve": 71.0, "chance": 71.0, "healthcare": 71.0, "series": 71.0, "tv": 71.0, "unemployment": 71.0, "usps": 71.0, "sterilization": 71.0, "gop": 71.0, "heart": 71.0, "detail": 70.0, "focus": 70.0, "food": 70.0, "link": 70.0, "deliver": 70.0, "tuesday": 70.0, "entire": 69.0, "thread": 69.0, "follow": 69.0, "st": 69.0, "source": 69.0, "exclusive": 69.0, "street": 69.0, "wrong": 69.0, "postal": 69.0, "idea": 69.0, "russian": 69.0, "benefit": 68.0, "nba": 68.0, "chief": 68.0, "form": 68.0, "poorpeoplescampaign": 67.0, "increase": 67.0, "reach": 67.0, "drive": 67.0, "interest": 67.0, "major": 66.0, "award": 66.0, "publish": 66.0, "push": 66.0, "fair": 66.0, "warn": 66.0, "near": 66.0, "tape": 65.0, "file": 65.0, "neverforget": 65.0, "kind": 65.0, "dejoy": 65.0, "distance": 65.0, "endorse": 64.0, "final": 64.0, "taylor": 64.0, "explain": 63.0, "michael": 63.0, "list": 63.0, "require": 63.0, "board": 63.0, "role": 63.0, "mississippi": 63.0, "driver": 63.0, "opportunity": 63.0, "star": 63.0, "household": 63.0, "adult": 62.0, "criminal": 62.0, "side": 62.0, "red": 62.0, "fox": 62.0, "f": 62.0, "supreme": 62.0, "wnba": 62.0, "anniversary": 62.0, "episode": 62.0, "violence": 61.0, "mother": 61.0, "request": 61.0, "march": 61.0, "storm": 61.0, "struggle": 61.0, "whistleblower": 61.0, "john": 61.0, "fan": 61.0, "land": 61.0, "resign": 61.0, "amaze": 61.0, "campus": 61.0, "aid": 61.0, "mcconnell": 61.0, "elect": 61.0, "powerful": 60.0, "absolutely": 60.0, "supporter": 60.0, "term": 60.0, "date": 60.0, "olivia": 60.0, "view": 60.0, "saturday": 60.0, "article": 60.0, "agent": 60.0, "sick": 59.0, "tool": 59.0, "note": 59.0, "civil": 59.0, "treat": 59.0, "remind": 59.0, "recognize": 59.0, "wray": 59.0, "nfl": 58.0, "poor": 58.0, "cost": 58.0, "pennsylvania": 58.0, "goal": 58.0, "wisconsin": 58.0, "doctor": 58.0, "soon": 58.0, "witness": 58.0, "organize": 57.0, "forest": 57.0, "extend": 57.0, "expert": 57.0, "rich": 57.0, "legislation": 57.0, "track": 57.0, "china": 57.0, "pro": 57.0, "clipper": 57.0, "false": 57.0, "abuse": 57.0, "ag": 56.0, "doj": 56.0, "sky": 56.0, "girl": 56.0, "organization": 56.0, "resident": 56.0, "train": 56.0, "promise": 56.0, "victory": 56.0, "medical": 56.0, "pre": 56.0, "fine": 55.0, "theory": 55.0, "assault": 55.0, "global": 55.0, "weekend": 55.0, "add": 55.0, "dead": 55.0, "travel": 55.0, "journalist": 54.0, "accuse": 54.0, "wind": 54.0, "author": 54.0, "light": 54.0, "deputy": 54.0, "email": 54.0, "ca": 54.0, "leadership": 54.0, "practice": 54.0, "thursday": 54.0, "represent": 53.0, "letter": 53.0, "wing": 53.0, "discussion": 53.0, "couldn": 53.0, "walk": 53.0, "emergency": 53.0, "congrats": 53.0, "hate": 53.0, "tie": 53.0, "troye": 53.0, "apply": 53.0, "commit": 53.0, "remove": 53.0, "athlete": 53.0, "total": 52.0, "freedom": 52.0, "damage": 52.0, "reform": 52.0, "wh": 52.0, "wednesday": 52.0, "phone": 52.0, "brother": 52.0, "coach": 52.0, "dollar": 52.0, "choose": 52.0, "shut": 52.0, "retweet": 51.0, "respect": 51.0, "control": 51.0, "april": 51.0, "daily": 51.0, "laborday": 51.0, "perform": 51.0, "downplay": 51.0, "https": 51.0, "worth": 51.0, "restaurant": 51.0, "lawyer": 51.0, "lawsuit": 50.0, "energy": 50.0, "racist": 50.0, "pick": 50.0, "louis": 50.0, "photo": 50.0, "prevent": 50.0, "playoff": 50.0, "research": 50.0, "george": 50.0, "advance": 50.0, "prosecutor": 50.0, "hey": 50.0, "breonna": 50.0, "church": 50.0, "solidarity": 50.0, "heat": 50.0, "washington": 50.0, "panic": 50.0, "buy": 50.0, "mayor": 50.0, "attempt": 50.0, "ahead": 50.0, "contract": 49.0, "refuse": 49.0, "multiple": 49.0, "disaster": 49.0, "current": 49.0, "thrill": 49.0, "alabama": 49.0, "son": 49.0, "secretary": 49.0, "aren": 49.0, "process": 49.0, "age": 49.0, "democratic": 49.0, "room": 49.0, "deep": 49.0, "reality": 49.0, "debate": 49.0, "evidence": 49.0, "color": 48.0, "east": 48.0, "birthday": 48.0, "affect": 48.0, "grow": 48.0, "compare": 48.0, "sunday": 48.0, "fauci": 48.0, "poverty": 48.0, "effect": 48.0, "majority": 48.0, "round": 48.0, "highlight": 48.0, "massif": 48.0, "ed": 48.0, "protester": 48.0, "model": 48.0, "devastate": 48.0, "inspire": 47.0, "patient": 47.0, "rep": 47.0, "al": 47.0, "value": 47.0, "facility": 47.0, "sen": 47.0, "reporter": 47.0, "beautiful": 47.0, "urge": 47.0, "wi": 47.0, "strategy": 47.0, "half": 47.0, "partner": 46.0, "recent": 46.0, "number": 46.0, "personal": 46.0, "mike": 46.0, "pretty": 46.0, "wouldn": 46.0, "minimum": 46.0, "insurance": 46.0, "destroy": 46.0, "slow": 46.0, "complete": 46.0, "motivate": 46.0, "grateful": 46.0, "art": 46.0, "battle": 46.0, "defense": 45.0, "scientific": 45.0, "wasn": 45.0, "consider": 45.0, "providence": 45.0, "encourage": 45.0, "park": 45.0, "legal": 45.0, "hispanic": 45.0, "pressure": 45.0, "shouldn": 45.0, "baby": 45.0, "1st": 45.0, "promote": 45.0, "stream": 45.0, "absentee": 45.0, "colleague": 45.0, "front": 45.0, "ban": 44.0, "corporation": 44.0, "trial": 44.0, "responder": 44.0, "podcast": 44.0, "pull": 44.0, "explore": 44.0, "worry": 44.0, "finish": 44.0, "patriotic": 44.0, "atlantic": 44.0, "expand": 44.0, "defend": 44.0, "seek": 44.0, "october": 44.0, "silence": 44.0, "alert": 44.0, "registration": 44.0, "fill": 44.0, "limit": 43.0, "testify": 43.0, "beat": 43.0, "gonna": 43.0, "wealth": 43.0, "produce": 43.0, "favorite": 43.0, "evacuation": 43.0, "neighbor": 43.0, "israel": 43.0, "acre": 43.0, "quality": 43.0, "herd": 43.0, "normal": 43.0, "clean": 43.0, "inside": 43.0, "flash": 43.0, "average": 43.0, "account": 42.0, "engage": 42.0, "tip": 42.0, "page": 42.0, "gulf": 42.0, "digital": 42.0, "target": 42.0, "admit": 42.0, "vice": 42.0, "introduce": 42.0, "incredible": 42.0, "site": 42.0, "catch": 42.0, "decide": 42.0, "wonderful": 42.0, "flu": 42.0, "bus": 41.0, "chair": 41.0, "harris": 41.0, "politically": 41.0, "grind": 41.0, "nominee": 41.0, "horrific": 41.0, "obama": 41.0, "professor": 41.0, "senior": 41.0, "amendment": 41.0, "bar": 41.0, "music": 41.0, "citizen": 41.0, "abc": 41.0, "comment": 41.0, "soul": 41.0, "paul": 41.0, "difference": 41.0, "mislead": 41.0, "criticize": 41.0, "huge": 41.0, "reject": 41.0, "august": 41.0, "potential": 41.0, "7pm": 41.0, "qanon": 41.0, "attention": 41.0, "eat": 40.0, "fast": 40.0, "disease": 40.0, "michigan": 40.0, "commitment": 40.0, "mvp": 40.0, "expose": 40.0, "planet": 40.0, "vp": 40.0, "water": 40.0, "injustice": 40.0, "victim": 40.0, "los": 40.0, "relate": 40.0, "artist": 40.0, "enforcement": 40.0, "schedule": 40.0, "mom": 39.0, "enjoy": 39.0, "trade": 39.0, "quote": 39.0, "brown": 39.0, "mission": 39.0, "double": 39.0, "unleash": 39.0, "strength": 39.0, "deny": 39.0, "foreign": 39.0, "effective": 39.0, "caputo": 39.0, "father": 39.0, "assistance": 39.0, "amount": 38.0, "oct": 38.0, "blame": 38.0, "car": 38.0, "conservative": 38.0, "approach": 38.0, "international": 38.0, "lyft": 38.0, "simple": 38.0, "road": 38.0, "fellow": 38.0, "smart": 38.0, "louisville": 38.0, "conspiracy": 38.0, "fun": 38.0, "ride": 38.0, "william": 38.0, "box": 38.0, "crew": 38.0, "allege": 37.0, "fake": 37.0, "assembly": 37.0, "nevada": 37.0, "document": 37.0, "mental": 37.0, "sexual": 37.0, "generation": 37.0, "advocate": 37.0, "simply": 37.0, "agreement": 37.0, "mind": 37.0, "performance": 37.0, "boy": 37.0, "russia": 37.0, "carry": 37.0, "admin": 37.0, "aide": 37.0, "present": 37.0, "guess": 37.0, "delay": 37.0, "central": 37.0, "measure": 37.0, "industry": 37.0, "19th": 37.0, "price": 37.0, "private": 37.0, "texas": 37.0, "flight": 37.0, "agency": 37.0, "super": 37.0, "activist": 37.0, "homeland": 36.0, "haven": 36.0, "course": 36.0, "picture": 36.0, "platform": 36.0, "constitutionday": 36.0, "prison": 36.0, "foot": 36.0, "opinion": 36.0, "deadline": 36.0, "reduce": 36.0, "loss": 36.0, "finally": 36.0, "gov": 36.0, "ceo": 36.0, "direct": 36.0, "attend": 36.0, "upcoming": 36.0, "extreme": 36.0, "blood": 36.0, "lesson": 36.0, "easy": 36.0, "genocide": 36.0, "allegation": 36.0, "contact": 36.0, "improve": 36.0, "executive": 36.0, "prop": 36.0, "gun": 36.0, "el": 35.0, "internet": 35.0, "rush": 35.0, "committee": 35.0, "regular": 35.0, "website": 35.0, "importance": 35.0, "review": 35.0, "bidentownhall": 35.0, "cast": 35.0, "violent": 35.0, "blow": 35.0, "connect": 35.0, "market": 35.0, "speech": 35.0, "cool": 35.0, "harm": 35.0, "interfere": 35.0, "investigate": 35.0, "hell": 35.0, "brand": 34.0, "yell": 34.0, "match": 34.0, "collins": 34.0, "flag": 34.0, "christian": 34.0, "camp": 34.0, "cancer": 34.0, "daughter": 34.0, "equal": 34.0, "ongoing": 34.0, "summer": 34.0, "public_school": 34.0, "sound": 34.0, "dad": 34.0, "february": 34.0, "loser": 34.0, "treatment": 34.0, "quarter": 34.0, "financial": 34.0, "significant": 34.0, "latino": 34.0, "dhs": 34.0, "activity": 34.0, "sister": 34.0, "uber": 34.0, "lack": 34.0, "western": 34.0, "exist": 34.0, "pray": 34.0, "title": 34.0, "stewart": 33.0, "mitch": 33.0, "position": 33.0, "station": 33.0, "movie": 33.0, "grant": 33.0, "avoid": 33.0, "historian": 33.0, "dawn": 33.0, "survey": 33.0, "door": 33.0, "honest": 33.0, "prayer": 33.0, "zoom": 33.0, "robert": 33.0, "suppose": 33.0, "category": 33.0, "figure": 33.0, "june": 33.0, "op": 33.0, "pt": 33.0, "nc": 33.0, "supremacist": 33.0, "2020census": 33.0, "rookie": 33.0, "individual": 33.0, "bank": 33.0, "cry": 33.0, "1u": 33.0, "eye": 33.0, "info": 32.0, "evacuate": 32.0, "jim": 32.0, "secret": 32.0, "weather": 32.0, "funny": 32.0, "tropical": 32.0, "division": 32.0, "ticket": 32.0, "postmaster": 32.0, "king": 32.0, "navidafkari": 32.0, "champion": 32.0, "rest": 32.0, "amid": 32.0, "development": 32.0, "crazy": 32.0, "body": 32.0, "arrive": 32.0, "imagine": 32.0, "commission": 32.0, "troop": 32.0, "ally": 32.0, "debt": 32.0, "cop": 32.0, "authority": 32.0, "september11": 31.0, "subject": 31.0, "decline": 31.0, "hasn": 31.0, "prof": 31.0, "tough": 31.0, "pack": 31.0, "image": 31.0, "tree": 31.0, "yard": 31.0, "donate": 31.0, "bridge": 31.0, "inform": 31.0, "resume": 31.0, "clinton": 31.0, "suffer": 31.0, "design": 31.0, "fear": 31.0, "jon": 31.0, "drink": 31.0, "hurt": 31.0, "fee": 31.0, "wash": 31.0, "hhs": 31.0, "gas": 31.0, "solution": 31.0, "click": 31.0, "safely": 30.0, "panel": 30.0, "argument": 30.0, "stake": 30.0, "indoor": 30.0, "chinese": 30.0, "hot": 30.0, "nov": 30.0, "dream": 30.0, "film": 30.0, "afford": 30.0, "relationship": 30.0, "bipartisan": 30.0, "dems": 30.0, "putin": 30.0, "webinar": 30.0, "rage": 30.0, "mr": 30.0, "roll": 30.0, "moderate": 30.0, "percent": 30.0, "professional": 30.0, "basic": 30.0, "mandate": 30.0, "earn": 30.0, "invest": 30.0, "gender": 30.0, "guard": 30.0, "stock": 30.0, "breonnataylor": 30.0, "july": 30.0, "mile": 30.0, "basically": 30.0, "partisan": 30.0, "sox": 30.0, "espn": 30.0, "ohio": 30.0, "moralmonday": 30.0, "thought": 30.0, "connecticut": 30.0, "faith": 29.0, "wealthy": 29.0, "cdt": 29.0, "terrorist": 29.0, "eviction": 29.0, "danger": 29.0, "owner": 29.0, "network": 29.0, "landfall": 29.0, "participate": 29.0, "hill": 29.0, "wed": 29.0, "directly": 29.0, "lift": 29.0, "airline": 29.0, "faculty": 29.0, "taxpayer": 29.0, "confuse": 29.0, "fl": 29.0, "southern": 29.0, "efficiency": 29.0, "disinformation": 29.0, "nysut": 29.0, "damn": 29.0, "culture": 29.0, "restore": 29.0, "accept": 29.0, "confront": 29.0, "short": 29.0, "dark": 29.0, "brave": 29.0, "nationwide": 29.0, "supremacy": 29.0, "hispanicheritagemonth": 29.0, "intelligence": 29.0, "dear": 29.0, "romney": 29.0, "dog": 29.0, "james": 28.0, "stimulus": 28.0, "iranian": 28.0, "spot": 28.0, "african": 28.0, "influence": 28.0, "repeat": 28.0, "uic": 28.0, "common": 28.0, "song": 28.0, "sense": 28.0, "recovery": 28.0, "border": 28.0, "hide": 28.0, "additional": 28.0, "accountable": 28.0, "handle": 28.0, "evangelical": 28.0, "lifetime": 28.0, "moral": 28.0, "winner": 28.0, "army": 28.0, "gather": 28.0, "peter": 28.0, "courage": 28.0, "iran": 28.0, "failure": 28.0, "violation": 28.0, "immediately": 28.0, "youth": 28.0, "depend": 28.0, "memory": 28.0, "stuff": 28.0, "surge": 28.0, "bite": 28.0, "legacy": 27.0, "choice": 27.0, "mobile": 27.0, "myth": 27.0, "advice": 27.0, "rescue": 27.0, "growth": 27.0, "crowd": 27.0, "abolish": 27.0, "recover": 27.0, "weekly": 27.0, "gain": 27.0, "hazard": 27.0, "field": 27.0, "rank": 27.0, "holy": 27.0, "remarkable": 27.0, "capture": 27.0, "develop": 27.0, "store": 27.0, "immunity": 27.0, "wife": 27.0, "brain": 27.0, "standard": 27.0, "bahrain": 27.0, "irwin": 27.0, "amazon": 27.0, "proposal": 27.0, "operation": 27.0, "drug": 27.0, "tiktok": 27.0, "layoff": 27.0, "holocaust": 27.0, "nbc": 27.0, "viral": 27.0, "society": 27.0, "vindman": 27.0, "implement": 27.0, "conduct": 27.0, "graham": 27.0, "dedicate": 27.0, "paper": 27.0, "space": 27.0, "icymi": 27.0, "electoral": 27.0, "wit": 27.0, "plane": 27.0, "execution": 27.0, "hire": 27.0, "workplace": 27.0, "situation": 27.0, "found": 27.0, "outrage": 27.0, "reusable": 27.0, "independent": 27.0, "rewrite": 27.0, "appear": 27.0, "shout": 27.0, "deeply": 26.0, "sell": 26.0, "reflect": 26.0, "app": 26.0, "steve": 26.0, "management": 26.0, "politician": 26.0, "officially": 26.0, "undermine": 26.0, "suggest": 26.0, "approve": 26.0, "century": 26.0, "convention": 26.0, "shit": 26.0, "guide": 26.0, "surprise": 26.0, "rapidly": 26.0, "protectallworkers": 26.0, "denver": 26.0, "ass": 26.0, "ppl": 26.0, "essay": 26.0, "jesus": 26.0, "nys": 26.0, "express": 26.0, "realdonaldtrump": 26.0, "outcome": 26.0, "condemn": 26.0, "kick": 26.0, "feed": 26.0, "misinformation": 26.0, "apparently": 26.0, "scholar": 26.0, "search": 26.0, "secure": 26.0, "pelosi": 26.0, "joebiden": 26.0, "poster": 26.0, "argue": 25.0, "kawhi": 25.0, "suicide": 25.0, "degree": 25.0, "donation": 25.0, "incident": 25.0, "progress": 25.0, "assist": 25.0, "extremely": 25.0, "dozen": 25.0, "strange": 25.0, "pentagon": 25.0, "fix": 25.0, "camera": 25.0, "libertyloud": 25.0, "sc": 25.0, "jail": 25.0, "depression": 25.0, "wake": 25.0, "supply": 25.0, "partnership": 25.0, "virginia": 25.0, "customer": 25.0, "scene": 25.0, "amy": 25.0, "endorsement": 25.0, "howard": 25.0, "delivery": 25.0, "original": 25.0, "para": 25.0, "angeles": 25.0, "kentucky": 25.0, "delaware": 25.0, "healthy": 25.0, "glad": 25.0, "rely": 25.0, "rainfall": 25.0, "wooten": 25.0, "fully": 25.0, "difficult": 25.0, "sec": 25.0, "born": 25.0, "disgust": 25.0, "weapon": 25.0, "equity": 25.0, "sponsor": 25.0, "gate": 25.0, "conflict": 25.0, "ignore": 25.0, "ridiculous": 25.0, "straight": 25.0, "plant": 25.0, "location": 24.0, "sp": 24.0, "magazine": 24.0, "antifa": 24.0, "primary": 24.0, "settlement": 24.0, "nj": 24.0, "systemic": 24.0, "equality": 24.0, "abortion": 24.0, "documentary": 24.0, "shock": 24.0, "phase": 24.0, "consequence": 24.0, "unprecedented": 24.0, "throw": 24.0, "billionaire": 24.0, "con": 24.0, "tour": 24.0, "evil": 24.0, "virtually": 24.0, "invite": 24.0, "purpose": 24.0, "perspective": 24.0, "sep": 24.0, "volunteer": 24.0, "16th": 24.0, "prize": 24.0, "disturb": 24.0, "bay": 24.0, "remote": 24.0, "classroom": 24.0, "memorial": 24.0, "property": 24.0, "jr": 24.0, "quickly": 24.0, "4pm": 24.0, "notice": 24.0, "chris": 24.0, "sentence": 24.0, "emerge": 24.0, "status": 24.0, "quick": 24.0, "jackson": 24.0, "population": 24.0, "nice": 24.0, "privilege": 24.0, "rend": 24.0, "occur": 24.0, "chip": 24.0, "ui": 24.0, "mid": 24.0, "christians": 24.0, "symptom": 24.0, "solve": 24.0, "institution": 24.0, "fly": 24.0, "deploy": 24.0, "examine": 23.0, "english": 23.0, "http": 23.0, "bubble": 23.0, "wild": 23.0, "speaker": 23.0, "crucial": 23.0, "technology": 23.0, "facemarks": 23.0, "analysis": 23.0, "credit": 23.0, "bless": 23.0, "dorris": 23.0, "lou": 23.0, "appointment": 23.0, "guest": 23.0, "liberty": 23.0, "wide": 23.0, "forever": 23.0, "canada": 23.0, "determine": 23.0, "johnson": 23.0, "farm": 23.0, "stage": 23.0, "combine": 23.0, "unionstrong": 23.0, "employer": 23.0, "ar": 23.0, "celebration": 23.0, "positivity": 23.0, "researcher": 23.0, "angry": 23.0, "grade": 23.0, "steven": 23.0, "durham": 23.0, "direction": 23.0, "cash": 23.0, "ap": 23.0, "donor": 23.0, "shift": 23.0, "language": 23.0, "recently": 23.0, "guidance": 23.0, "contribution": 23.0, "propose": 23.0, "msnbc": 23.0, "retweets": 23.0, "bush": 23.0, "oppose": 23.0, "mobilize": 22.0, "publicly": 22.0, "modern": 22.0, "extension": 22.0, "dan": 22.0, "league": 22.0, "draw": 22.0, "text": 22.0, "actual": 22.0, "declare": 22.0, "obtain": 22.0, "guarantee": 22.0, "repeatedly": 22.0, "bomb": 22.0, "violate": 22.0, "deport": 22.0, "diversity": 22.0, "priority": 22.0, "arm": 22.0, "congressional": 22.0, "legitimate": 22.0, "orange": 22.0, "louisiana": 22.0, "consent": 22.0, "rare": 22.0, "table": 22.0, "remark": 22.0, "audio": 22.0, "propaganda": 22.0, "tribute": 22.0, "2nd": 22.0, "path": 22.0, "defeat": 22.0, "gen": 22.0, "annual": 22.0, "region": 22.0, "kevin": 22.0, "screen": 22.0, "steal": 22.0, "statewide": 22.0, "3rd": 22.0, "belief": 22.0, "connection": 22.0, "infect": 22.0, "transition": 22.0, "ain": 22.0, "pts": 22.0, "terrible": 22.0, "wolf": 22.0, "capitol": 22.0, "chicago": 22.0, "bc": 22.0, "liberal": 22.0, "blacklivesmatter": 21.0, "shake": 21.0, "extra": 21.0, "wa": 21.0, "absurd": 21.0, "license": 21.0, "lgbtq": 21.0, "behavior": 21.0, "11th": 21.0, "outstanding": 21.0, "breathe": 21.0, "loan": 21.0, "advisory": 21.0, "brooklyn": 21.0, "dumb": 21.0, "sustain": 21.0, "smile": 21.0, "minister": 21.0, "ceremony": 21.0, "island": 21.0, "furlough": 21.0, "brilliant": 21.0, "nyt": 21.0, "blackburn": 21.0, "cancel": 21.0, "writer": 21.0, "hurricanesally": 21.0, "mexico": 21.0, "detain": 21.0, "loud": 21.0, "fuck": 21.0, "assistant": 21.0, "knowledge": 21.0, "nugget": 21.0, "distribute": 21.0, "speed": 21.0, "colorado": 21.0, "jews": 21.0, "scranton": 21.0, "organizer": 21.0, "describe": 21.0, "frontline": 21.0, "arizona": 21.0, "wall": 21.0, "package": 21.0, "illegal": 21.0, "sacrifice": 21.0, "tackle": 21.0, "ball": 21.0, "agenda": 21.0, "transit": 21.0, "column": 21.0, "withhold": 21.0, "collection": 21.0, "fuel": 21.0, "venir": 21.0, "stick": 20.0, "latinx": 20.0, "humanity": 20.0, "realize": 20.0, "td": 20.0, "identify": 20.0, "fo": 20.0, "creekfire": 20.0, "scream": 20.0, "prefer": 20.0, "bottom": 20.0, "marsha": 20.0, "route": 20.0, "miami": 20.0, "universal": 20.0, "lab": 20.0, "complaint": 20.0, "4th": 20.0, "edt": 20.0, "widely": 20.0, "alarm": 20.0, "wanna": 20.0, "blast": 20.0, "zone": 20.0, "religion": 20.0, "rape": 20.0, "execute": 20.0, "lay": 20.0, "reaction": 20.0, "favor": 20.0, "trend": 20.0, "rsvp": 20.0, "avenue": 20.0, "preserve": 20.0, "horror": 20.0, "calm": 20.0, "range": 20.0, "aware": 20.0, "engagement": 20.0, "heroesact": 20.0, "pastor": 20.0, "rain": 20.0, "empty": 20.0, "whitesox": 20.0, "employment": 20.0, "lake": 20.0, "duty": 20.0, "circuit": 20.0, "square": 20.0, "profit": 20.0, "gap": 20.0, "unionize": 20.0, "seat": 20.0, "payment": 20.0, "card": 20.0, "everyday": 20.0, "adviser": 20.0, "sheriff": 20.0, "alex": 20.0, "prove": 20.0, "lebron": 19.0, "completely": 19.0, "illness": 19.0, "dinner": 19.0, "print": 19.0, "user": 19.0, "strikeforourlives": 19.0, "pr": 19.0, "stun": 19.0, "innocent": 19.0, "sexually": 19.0, "otd": 19.0, "native": 19.0, "sterilize": 19.0, "bear": 19.0, "survive": 19.0, "journey": 19.0, "mention": 19.0, "wilson": 19.0, "accessible": 19.0, "san": 19.0, "type": 19.0, "addie": 19.0, "infection": 19.0, "domestic": 19.0, "jump": 19.0, "confidence": 19.0, "mistake": 19.0, "session": 19.0, "peaceful": 19.0, "iron": 19.0, "medicare": 19.0, "judicial": 19.0, "mae": 19.0, "weird": 19.0, "hotel": 19.0, "compromise": 19.0, "renew": 19.0, "ct": 19.0, "slam": 19.0, "ambush": 19.0, "announcement": 19.0, "trillion": 19.0, "floyd": 19.0, "yo": 19.0, "russians": 19.0, "separation": 19.0, "application": 19.0, "heavy": 19.0, "tom": 19.0, "responsible": 19.0, "beach": 19.0, "procedure": 19.0, "vehicle": 19.0, "aim": 19.0, "actively": 19.0, "dakota": 19.0, "tear": 19.0, "atlanta": 19.0, "frontlines": 19.0}